termial_random/random.cpython-38-x86_64-linux-gnu.so
termial_random/__init__.py
termial_random-0.0.2.dist-info/top_level.txt
termial_random-0.0.2.dist-info/METADATA
termial_random-0.0.2.dist-info/RECORD
termial_random-0.0.2.dist-info/LICENSE
termial_random-0.0.2.dist-info/WHEEL
