Metadata-Version: 1.1
Name: termial-random
Version: 0.0.2
Summary: Extensions to standard Python's heapq for performance applications
Home-page: https://github.com/thoth-station/termial-random
Author: Fridolin Pokorny
Author-email: fridolin@redhat.com
License: GPLv3+
Download-URL: https://pypi.org/project/termial-random
Platform: UNKNOWN
